threat_scanner/__init__.py
threat_scanner/cloud_inference.py
threat_scanner/detector.py
threat_scanner/email_alert.py
threat_scanner/kinetics_600_labels.json
threat_scanner/utils.py
threat_scanner-0.1.3.dist-info/LICENSE
threat_scanner-0.1.3.dist-info/METADATA
threat_scanner-0.1.3.dist-info/WHEEL
threat_scanner-0.1.3.dist-info/top_level.txt
threat_scanner-0.1.3.dist-info/RECORD
