Metadata-Version: 2.1
Name: threat-scanner
Version: 0.1.3
Summary: Detect threats in videos using MovieNet locally or via Vertex AI.
Home-page: https://github.com/threatscan-ai/threatscan
Author: Ogo-Oluwasubomi Popoola
Author-email: 52616005+popoolasubomi@users.noreply.github.com
License: MIT
Project-URL: Bug Tracker, https://github.com/threatscan-ai/threatscan/issues
Project-URL: Source Code, https://github.com/threatscan-ai/threatscan
Project-URL: Documentation, https://github.com/threatscan-ai/threatscan/blob/main/README.md
Keywords: vertex ai,video analysis,threat detection,action recognition,movienet,google cloud
Classifier: Programming Language :: Python :: 3
Classifier: License :: OSI Approved :: MIT License
Classifier: Operating System :: OS Independent
Classifier: Intended Audience :: Developers
Classifier: Topic :: Scientific/Engineering :: Artificial Intelligence
Classifier: Topic :: Software Development :: Libraries :: Python Modules
Classifier: Topic :: Security
Requires-Python: >=3.8
License-File: LICENSE
Requires-Dist: google-cloud-aiplatform (>=1.25.0)
Requires-Dist: google-auth (>=2.6.0)
Requires-Dist: sendgrid (>=6.9.0)
Requires-Dist: numpy (>=1.21.0)
